<?xml version = "1.0" encoding = "utf-8"?>
<!DOCTYPE hibernate-mapping PUBLIC
    "-//Hibernate/Hibernate Mapping DTD//EN"
    "http://www.hibernate.org/dtd/hibernate-mapping-3.0.dtd">

<hibernate-mapping>
  <class name = "object.SqlQuestion" table = "Questions">

    <meta attribute = "class-description">
      Questions stuff.
    </meta>

    <id name = "id" type = "int" column = "id">
      <generator class="native"/>
    </id>
    <property name = "question" column = "Question" type = "string"/>
    <property name = "answer" column = "Answer" type = "string"/>

  </class>
</hibernate-mapping>